nrfcloud_utils/__init__.py
nrfcloud_utils/ca_certs.py
nrfcloud_utils/claim_and_provision_device.py
nrfcloud_utils/claim_devices.py
nrfcloud_utils/cli_helpers.py
nrfcloud_utils/create_ca_cert.py
nrfcloud_utils/create_device_credentials.py
nrfcloud_utils/create_proxy_jwt.py
nrfcloud_utils/device_credentials_installer.py
nrfcloud_utils/gather_attestation_tokens.py
nrfcloud_utils/modem_credentials_parser.py
nrfcloud_utils/nrf_cloud_device_mgmt.py
nrfcloud_utils/nrf_cloud_diap.py
nrfcloud_utils/nrf_cloud_onboard.py
nrfcloud_utils-3.0.11.dist-info/METADATA
nrfcloud_utils-3.0.11.dist-info/WHEEL
nrfcloud_utils-3.0.11.dist-info/entry_points.txt
nrfcloud_utils-3.0.11.dist-info/licenses/LICENSE.txt
nrfcloud_utils-3.0.11.dist-info/RECORD
