Metadata-Version: 2.4
Name: nrfcloud-utils
Version: 3.0.11
Summary: Scripts and utilities for working with the nRF Cloud
License: BSD-3-Clause
License-File: LICENSE.txt
Author: Nordic Semiconductor ASA
Requires-Python: >=3.10,<4.0
Classifier: License :: OSI Approved :: BSD License
Classifier: Programming Language :: Python :: 3
Classifier: Programming Language :: Python :: 3.10
Classifier: Programming Language :: Python :: 3.11
Classifier: Programming Language :: Python :: 3.12
Classifier: Programming Language :: Python :: 3.13
Classifier: Programming Language :: Python :: 3.14
Requires-Dist: cbor2 (>=5.4.2.post1,<6.0.0)
Requires-Dist: cffi (>=1.17.1,<2.0.0)
Requires-Dist: cryptography (>=45.0.4,<46.0.0)
Requires-Dist: inquirer (>=3.4.0,<4.0.0)
Requires-Dist: nrfcredstore (>=2.0.9,<3.0.0)
Requires-Dist: pyjwt (>=2.3.0,<3.0.0)
Requires-Dist: requests (>=2.32.0,<3.0.0)
Requires-Dist: semver (>=3.0.0,<4.0.0)
Requires-Dist: urllib3 (>=2.2.2,<3.0.0)
Project-URL: Repository, https://github.com/nRFCloud/utils
